{
  "headers": {
    "age": "13626489",
    "x-amz-cf-id": "J-1SmPNUBbgPQsxDOF-Nl1i827UZyS3kXpo2p-cPpdtIjF0HFEtOiA==",
    "date": "Thu, 28 Dec 2023 01:09:10 GMT",
    "server-timing": "fetchSource;dur=4",
    "accept-ranges": "bytes",
    "cross-origin-resource-policy": "same-origin",
    "content-security-policy": "default-src 'none'; style-src 'unsafe-inline'; sandbox",
    "referrer-policy": "strict-origin-when-cross-origin",
    "vary": "Accept-Encoding, Origin",
    "x-content-type-options": "nosniff",
    "cross-origin-embedder-policy": "same-origin",
    "cache-control": "public, max-age=31536000, immutable",
    "server": "deno/gcp-europe-west3",
    "x-amz-cf-pop": "FRA56-P5",
    "last-modified": "Fri, 25 Mar 2022 13:32:48 GMT",
    "x-amz-replication-status": "COMPLETED",
    "x-amz-version-id": "bEw21i2lp8eAv3brtinka2T_yiomhn0J",
    "x-frame-options": "DENY",
    "content-type": "application/javascript",
    "etag": "W/\"10cd29565803a4d663f4fa3e96a81923\"",
    "access-control-allow-origin": "*",
    "strict-transport-security": "max-age=63072000; includeSubDomains; preload",
    "via": "http/2 edgeproxy-h",
    "x-cache": "Hit from cloudfront",
    "cross-origin-opener-policy": "same-origin"
  },
  "url": "https://deno.land/std@0.132.0/node/_crypto/crypto_browserify/browserify_aes/modes/cbc.js",
  "now": {
    "secs_since_epoch": 1717352238,
    "nanos_since_epoch": 207810768
  }
}