{
  "headers": {
    "x-frame-options": "DENY",
    "age": "13205421",
    "cross-origin-resource-policy": "same-origin",
    "content-security-policy": "default-src 'none'; style-src 'unsafe-inline'; sandbox",
    "via": "http/2 edgeproxy-h",
    "access-control-allow-origin": "*",
    "content-type": "application/javascript",
    "date": "Mon, 01 Jan 2024 22:06:23 GMT",
    "cross-origin-embedder-policy": "same-origin",
    "server-timing": "fetchSource;dur=52",
    "cross-origin-opener-policy": "same-origin",
    "vary": "Accept-Encoding, Origin",
    "x-amz-cf-id": "TO5vO9Ix49BUkdVC2UqgyZnIpopPdPO_1EdOBDkzjYj24km5aBdObQ==",
    "last-modified": "Fri, 25 Mar 2022 13:32:50 GMT",
    "x-amz-version-id": "YT_zt8pTyXYQLa6deTPNf9uwamHRsfvL",
    "etag": "W/\"e4ff114518de3374d29939ee8b2b04c6\"",
    "referrer-policy": "strict-origin-when-cross-origin",
    "cache-control": "public, max-age=31536000, immutable",
    "server": "deno/gcp-europe-west3",
    "strict-transport-security": "max-age=63072000; includeSubDomains; preload",
    "x-amz-cf-pop": "FRA56-P5",
    "x-amz-replication-status": "COMPLETED",
    "x-cache": "Hit from cloudfront",
    "x-content-type-options": "nosniff"
  },
  "url": "https://deno.land/std@0.132.0/node/internal/streams/transform.mjs",
  "now": {
    "secs_since_epoch": 1717352210,
    "nanos_since_epoch": 351866395
  }
}